Metadata-Version: 2.1
Name: mdb-parser
Version: 0.0.2
Summary: Microsoft Access (.mdb, .accdb) database file parser
Home-page: https://github.com/fedestella263/mdb_parser
Author: Federico Stella
Author-email: fedestella263@gmail.com
License: MIT
Platform: UNKNOWN
Classifier: Programming Language :: Python :: 3
Classifier: License :: OSI Approved :: MIT License
Classifier: Operating System :: OS Independent
Requires-Python: >=3.6
